mqtt_thread/MQTT_Thread.py
mqtt_thread/MQTT_Thread_bak.py
mqtt_thread/__init__.py
mqtt_thread-1.6.5.dist-info/LICENCE
mqtt_thread-1.6.5.dist-info/METADATA
mqtt_thread-1.6.5.dist-info/WHEEL
mqtt_thread-1.6.5.dist-info/top_level.txt
mqtt_thread-1.6.5.dist-info/RECORD
