Metadata-Version: 2.1
Name: mqtt-thread
Version: 1.6.5
Summary: Connection MQTT with thread
Author: Didier Orlandi
Author-email: didier.orlandi@wanadoo.fr
Classifier: Programming Language :: Python :: 3
Classifier: License :: OSI Approved :: MIT License
Classifier: Operating System :: OS Independent
Requires-Python: >=3.6
License-File: LICENCE
Requires-Dist: paho-mqtt
